pyunit_weather/__init__.py
pyunit_weather/address.zip
pyunit_weather/city.zip
pyunit_weather/weather.py
pyunit_weather-2019.3.1.dist-info/METADATA
pyunit_weather-2019.3.1.dist-info/WHEEL
pyunit_weather-2019.3.1.dist-info/top_level.txt
pyunit_weather-2019.3.1.dist-info/RECORD
