Metadata-Version: 2.1
Name: pyunit-weather
Version: 2019.3.1
Summary: 天气预报
Home-page: https://github.com/PyUnit/pyunit-weather
Author: Jtyoui
Author-email: jtyoui@qq.com
License: MIT Licence
Platform: any
Classifier: Programming Language :: Python :: 3
Classifier: License :: OSI Approved :: MIT License
Classifier: Operating System :: OS Independent
Requires-Dist: bs4 (==0.0.1)
Requires-Dist: fake-useragent (==0.1.11)
Requires-Dist: requests (==2.23.0)
